rosnet/__init__.py
rosnet/boost/__init__.py
rosnet/boost/_adaboost.py
rosnet/boost/_adastump.py
rosnet/decorator/__init__.py
rosnet/decorator/_methods.py
rosnet/metrics/__init__.py
rosnet/metrics/_classes.py
rosnet/neural_network/__init__.py
rosnet/neural_network/_sequential.py
rosnet/neural_network/activation/__init__.py
rosnet/neural_network/activation/_classes.py
rosnet/neural_network/layers/__init__.py
rosnet/neural_network/layers/_dence.py
rosnet/neural_network/optimizers/__init__.py
rosnet/neural_network/optimizers/_adam.py
rosnet/neural_network/optimizers/_classes.py
rosnet/neural_network/optimizers/_gradient_descent.py
rosnet/tree/__init__.py
rosnet/tree/_threshold.py
rosnet/tree/_treenode.py
rosnet/tree/threshold_.py
rosnet/tree/treenode_.py
rosnet/util/__init__.py
rosnet/util/_sampling.py
rosnet-0.3.2.dist-info/LICENSE
rosnet-0.3.2.dist-info/METADATA
rosnet-0.3.2.dist-info/WHEEL
rosnet-0.3.2.dist-info/top_level.txt
rosnet-0.3.2.dist-info/RECORD
