Metadata-Version: 2.1
Name: rosnet
Version: 0.3.2
Summary: Causal discovery with ML
Home-page: https://github.com/Ho-Jun-Moon/rosnet
Author: papamoon0113
Author-email: papamoon0113@pusan.ac.kr
License: UNKNOWN
Platform: UNKNOWN
Classifier: Programming Language :: Python :: 3
Classifier: License :: OSI Approved :: MIT License
Classifier: Operating System :: OS Independent
Requires-Python: >=3.6
License-File: LICENSE
Requires-Dist: numpy
